{
  "MailSubject": "REMPLACER PAR L'OBJET DU MAIL",
  "MailBodyTitle": "REMPLACER PAR LE TITRE DU MESSAGE",
  "MailBody": "Vous avez été désigné pour offrir un cadeau à <span style=\"font-weight: bold; color: yellow;\">{0}</span>.</br></br>Essayez de lui faire un cadeau personnalisé ! Renseignez-vous auprès des autres pour savoir ce qui lui ferait plaisir :-)</br></br><div>Joyeuses fêtes à tous, et gardez la surprise jusqu'au bout !</div>",
  "SmtpEmail": "email@mail.com",
  "SmtpPassword": "12345",
  "SmtpHost": "smtp.zoho.com",
  "SmtpPort": "465",
  "Participants": [
    {
      "Name": "Alice",
      "Email": "alice@mail.com"
    },
    {
      "Name": "Bob",
      "Email": "bob@mail.com"
    }
  ]
}